chess_ai/README.md
chess_ai/__init__.py
chess_ai/classical_agent/__init__.py
chess_ai/classical_agent/agent.py
chess_ai/classical_agent/evaluate_agent.py
chess_ai/evaluation/__init__.py
chess_ai/evaluation/utils.py
chess_ai/playground/__init__.py
chess_ai/playground/chess_cli.py
chess_ai/playground/chess_gui.py
chess_ai/playground/resources/black_bishop.png
chess_ai/playground/resources/black_king.png
chess_ai/playground/resources/black_knight.png
chess_ai/playground/resources/black_pawn.png
chess_ai/playground/resources/black_queen.png
chess_ai/playground/resources/black_rook.png
chess_ai/playground/resources/board.svg.png
chess_ai/playground/resources/pieces.svg.png
chess_ai/playground/resources/white_bishop.png
chess_ai/playground/resources/white_king.png
chess_ai/playground/resources/white_knight.png
chess_ai/playground/resources/white_pawn.png
chess_ai/playground/resources/white_queen.png
chess_ai/playground/resources/white_rook.png
chess_ai/rlagent/agent.py
chess_ai/rlagent/training/trainer.py
chess_ai_pip-0.1.5.dist-info/WHEEL
chess_ai_pip-0.1.5.dist-info/METADATA
chess_ai_pip-0.1.5.dist-info/RECORD
