Metadata-Version: 2.1
Name: chess-ai-pip
Version: 0.1.5
Summary: 
Author: pacanada
Author-email: pereirapcanada@gmail.com
Requires-Python: >=3.8,<4.0
Classifier: Programming Language :: Python :: 3
Classifier: Programming Language :: Python :: 3.8
Classifier: Programming Language :: Python :: 3.9
Classifier: Programming Language :: Python :: 3.10
Classifier: Programming Language :: Python :: 3.11
Requires-Dist: chess-python-pip (>=0.1.11,<0.2.0)
Requires-Dist: pyglet (>=1.5.27,<2.0.0)
